{
  "id": "1d8hrgx",
  "title": "Im killing myself in an hour and 6 minutes.",
  "selftext": "Please leave some final messages\n\n  \nEdit; 25 Minutes later and I have hope. My brother, who I havent seen or heard from in over half a decade, just replied to one of my texts. I've been catching up with him and I may have new hope.",
  "created_utc": 1717563256.0,
  "score": 705,
  "num_comments": 134,
  "url": "https://www.reddit.com/r/SuicideWatch/comments/1d8hrgx/im_killing_myself_in_an_hour_and_6_minutes/",
  "comments": [
    {
      "id": "l76jacs",
      "body": "i hope youre still talking with your brother. sometimes fate works in our favor. its not your time friend",
      "created_utc": 1717567824.0,
      "score": 194
    },
    {
      "id": "l76j5n6",
      "body": "Siblings really help, my sister has been my lifeline at times",
      "created_utc": 1717567740.0,
      "score": 211
    },
    {
      "id": "l76jnby",
      "body": "Please let us know you're ok OP 🫂",
      "created_utc": 1717568061.0,
      "score": 46
    },
    {
      "id": "l76ortz",
      "body": "Please don't do it",
      "created_utc": 1717571491.0,
      "score": 19
    },
    {
      "id": "l76oove",
      "body": "I’m glad that he reached out at the right time! Maybe it’s a sign from the Universe that it’s not your time to go; hang on, I know you’ll pull through! 🫂",
      "created_utc": 1717571433.0,
      "score": 22
    },
    {
      "id": "l76ct67",
      "body": "Don’t do it. The stars smile when they see you look up at them, if you push through you will look back with love in your heart and will have peace, I promise. You must never lose your grit, I’m in the same boat I want to die so  bad. Live and make the thoughts a memory",
      "created_utc": 1717563893.0,
      "score": 11
    },
    {
      "id": "l7720h7",
      "body": "Are you still there?",
      "created_utc": 1717581223.0,
      "score": 5
    },
    {
      "id": "l76igwb",
      "body": "Hi, tell us more about your brother and this renewed hope!",
      "created_utc": 1717567304.0,
      "score": 13
    },
    {
      "id": "l76mlcr",
      "body": "fate is real, he saved you now be there with him",
      "created_utc": 1717569994.0,
      "score": 4
    },
    {
      "id": "l77fg75",
      "body": "Please, reply if you are still alive.",
      "created_utc": 1717588879.0,
      "score": 5
    },
    {
      "id": "l76kmuq",
      "body": "Please don’t OP, glad your brother is here",
      "created_utc": 1717568701.0,
      "score": 7
    },
    {
      "id": "l76l9xi",
      "body": "Edit: 6 minutes",
      "created_utc": 1717569117.0,
      "score": 3
    },
    {
      "id": "l76x6p5",
      "body": "You doing okay? Just checking in. I hope you are okay. ❤️",
      "created_utc": 1717577710.0,
      "score": 3
    },
    {
      "id": "l76zenh",
      "body": "Glad you have hope but in case your world crashes down again just remember somebody out there does love you more than you know. Recently in the last few days my friends boyfriend killed himself and now shes in the hospital for an attempt and both of their families are steuggling tremendously. (Neither are close with their families but you don’t have to be close to someone for them to care)",
      "created_utc": 1717579358.0,
      "score": 3
    },
    {
      "id": "l77fci6",
      "body": "add my snap julzzzgeyerrr. please anyone who needs to talk. i’m 16 and struggle with severe mental health issues. i love helping help. it’s what im best at. especially mental health related. please stay. it gets better. ik you might not think so at the time. but trust, it does. it eventually does get better. i love you all.",
      "created_utc": 1717588830.0,
      "score": 3
    },
    {
      "id": "l797ddm",
      "body": "OP please let us know if you’re ok. If you’re still with us, don’t loose hope. Sometimes things are horrible and we just want to give up, but maybe if you just learn to find happiness in the little things you’ll gain the will to continue living even though it’s hard.",
      "created_utc": 1717611974.0,
      "score": 3
    },
    {
      "id": "l76e13c",
      "body": "What joys are you leaving behind? What would you regret if you stepped outside your body and realize that you’re now a ghost? Could you handle witnessing the sadness of those that know you if you became a ghost? What would change your mind in doing this, and is that very thing attainable?\n\nIf you ask enough questions, you’ll understand that suicide is not the right choice.",
      "created_utc": 1717564607.0,
      "score": 5
    },
    {
      "id": "l771ol7",
      "body": "Is it selfish of me to pretend I’m happy on the outside when on the inside I’m ready to go, yet delay it for the benefit of not upsetting people who don’t actively care about me? I’ve been in no contact with my ex & the way she ended it was scarring to me after everything she told me and we went through but her birthday is in 2 weeks and I don’t want to “ruin” it for her by ending it - but I cannot keep living like this",
      "created_utc": 1717580997.0,
      "score": 2
    },
    {
      "id": "l78b7cx",
      "body": "Sometimes we don't want to die. We just want connections. Glad you and your bro are in contact again.",
      "created_utc": 1717601195.0,
      "score": 2
    },
    {
      "id": "l7b4e0h",
      "body": "“You feel like dyin’, right? Bro it ain’t your time, all that cryin made me a menace\nYou feelin lost, right? No one here to find you, all that cryin made you a menace”\n\nHold on to hope, I’m grateful you made another choice ❤️‍🩹💪🏽",
      "created_utc": 1717637088.0,
      "score": 2
    },
    {
      "id": "l774cvi",
      "body": "Stay with us bromigo\nIt gets better",
      "created_utc": 1717582785.0,
      "score": 1
    },
    {
      "id": "l76znzy",
      "body": "I'm glad you were able to reconnect with your brother. I have a twin sister but we were separated at birth. I wish I had a chance to know her",
      "created_utc": 1717579549.0,
      "score": 1
    },
    {
      "id": "l775pru",
      "body": "Brothers! Yo there",
      "created_utc": 1717583645.0,
      "score": 1
    },
    {
      "id": "l775ylu",
      "body": "You are loved❤️",
      "created_utc": 1717583798.0,
      "score": 1
    },
    {
      "id": "l778rgb",
      "body": "How did your brother give you hope?",
      "created_utc": 1717585434.0,
      "score": 1
    },
    {
      "id": "l77dw4c",
      "body": "Dont give up",
      "created_utc": 1717588127.0,
      "score": 1
    },
    {
      "id": "l77esux",
      "body": "Please tell me you're still here, I know saying that life is precious might hurt you more but I really don't know what to say, but hang in there, even if your family isn't there, you still have your fellow Redditers.",
      "created_utc": 1717588567.0,
      "score": 1
    },
    {
      "id": "l77g9m6",
      "body": "Please tell me you didn't do it",
      "created_utc": 1717589277.0,
      "score": 1
    },
    {
      "id": "l77gsko",
      "body": "Hope you're still here. I see the edit and it gives me some hope you're still with us.",
      "created_utc": 1717589532.0,
      "score": 1
    },
    {
      "id": "l77i8o0",
      "body": "I hope you'll be ok and that you can really connect with your brother.",
      "created_utc": 1717590204.0,
      "score": 1
    },
    {
      "id": "l77lq9p",
      "body": "Glad you’re okay 🩵",
      "created_utc": 1717591772.0,
      "score": 1
    },
    {
      "id": "l77r4m3",
      "body": "I genuinely hope that the OP is alright now",
      "created_utc": 1717593986.0,
      "score": 1
    },
    {
      "id": "l77xql6",
      "body": "One of my favorite lyrics in a song that I listen to when I feel really fucked up and not okay is “End it all, but I won’t. I hold on to the one last thing I know. I got nothing left, but I guess I got hope”",
      "created_utc": 1717596493.0,
      "score": 1
    },
    {
      "id": "l78nnla",
      "body": "Please stay ❤️ you have survived every bad day your whole life so far! 100%! You will get through this.",
      "created_utc": 1717605359.0,
      "score": 1
    },
    {
      "id": "l78rcor",
      "body": "op whats going on",
      "created_utc": 1717606588.0,
      "score": 1
    },
    {
      "id": "l78sn5v",
      "body": "Your brother seems like a good guy, I'm sure he will get you through",
      "created_utc": 1717607025.0,
      "score": 1
    },
    {
      "id": "l78ttl1",
      "body": "Please give ur brother a chance and make it out as good as u can, make it a real good time wich give u more hope to survive ur ideation",
      "created_utc": 1717607424.0,
      "score": 1
    },
    {
      "id": "l78wbak",
      "body": "Hey man, you better now?",
      "created_utc": 1717608264.0,
      "score": 1
    },
    {
      "id": "l78zhqw",
      "body": "Please take your brother suddenly responding to you as a sign.",
      "created_utc": 1717609351.0,
      "score": 1
    },
    {
      "id": "l7922fj",
      "body": "I hope you’re doing ok pal! \nLife isn’t easy, continuous struggle but there’s always the “what may be next” question that keeps many of us here 😉",
      "created_utc": 1717610217.0,
      "score": 1
    },
    {
      "id": "l7931m2",
      "body": "Reconnect with your brother! Hope you're around to see this still op",
      "created_utc": 1717610544.0,
      "score": 1
    },
    {
      "id": "l7951bu",
      "body": "Hope you're well! Huge hug from a fellow depressed person, it will get better sometimes, just not always...",
      "created_utc": 1717611195.0,
      "score": 1
    },
    {
      "id": "l7958ve",
      "body": "That was a sign.",
      "created_utc": 1717611263.0,
      "score": 1
    },
    {
      "id": "l79fluw",
      "body": "Ideally you find your own meaning, not relying on others. Sigh.",
      "created_utc": 1717614721.0,
      "score": 1
    },
    {
      "id": "l79i7o0",
      "body": "hope is there. it’s always there.",
      "created_utc": 1717615592.0,
      "score": 1
    },
    {
      "id": "l7a1xiz",
      "body": "Everything happens for a reason friend remember it gets better 🩷",
      "created_utc": 1717622181.0,
      "score": 1
    },
    {
      "id": "l7a66o5",
      "body": "Are you okay?",
      "created_utc": 1717623669.0,
      "score": 1
    },
    {
      "id": "l7a7dv3",
      "body": "Don’t do it!! You’ll leave everyone around you in such pain. It’s just not worth it imho.",
      "created_utc": 1717624092.0,
      "score": 1
    },
    {
      "id": "l7aa86y",
      "body": "Are you okay?",
      "created_utc": 1717625113.0,
      "score": 1
    },
    {
      "id": "l7aahcs",
      "body": "Are you okay?",
      "created_utc": 1717625207.0,
      "score": 1
    },
    {
      "id": "l7ancm8",
      "body": "Hey brother wru ??? Plssss reply...u remember me ..I came back ?",
      "created_utc": 1717630137.0,
      "score": 1
    },
    {
      "id": "l7awef9",
      "body": "Hey just checking in to make sure you're alive",
      "created_utc": 1717633781.0,
      "score": 1
    },
    {
      "id": "l7b4a60",
      "body": "Please get in contact with your brother it will be worth it",
      "created_utc": 1717637042.0,
      "score": 1
    },
    {
      "id": "l7bwa9g",
      "body": "OP are you doing ok ?",
      "created_utc": 1717650171.0,
      "score": 1
    },
    {
      "id": "l7by6d6",
      "body": "that's good, almost a miracle",
      "created_utc": 1717651281.0,
      "score": 1
    },
    {
      "id": "l7ccjob",
      "body": "Im so happy you brother contacted you! You deserve life.",
      "created_utc": 1717660880.0,
      "score": 1
    },
    {
      "id": "l7cn2p8",
      "body": "Better not have done it man, if you got over that intense feeling of wanting to do it last night you can get over anything, we live life one day at a time, miracles can happen at anytime so just hold on.",
      "created_utc": 1717668524.0,
      "score": 1
    },
    {
      "id": "l7dlpva",
      "body": "Thinking of you",
      "created_utc": 1717684355.0,
      "score": 1
    },
    {
      "id": "l7do5q7",
      "body": "This life is a test for a new life…. The strongest gets given the hardest battles. Stay strong",
      "created_utc": 1717685202.0,
      "score": 1
    },
    {
      "id": "l7s5h1e",
      "body": "Isn't it wild sometimes things happen for us. It's like the Truman Show",
      "created_utc": 1717914517.0,
      "score": 1
    },
    {
      "id": "l7sr7yq",
      "body": "God loves you.🩷",
      "created_utc": 1717930197.0,
      "score": 1
    },
    {
      "id": "l82p1f5",
      "body": "It is awesome that your brother called.  That is a sign.  I really hope that you are okay now.",
      "created_utc": 1718082640.0,
      "score": 1
    },
    {
      "id": "l7ikzsg",
      "body": "Send me money before you die",
      "created_utc": 1717761633.0,
      "score": 0
    },
    {
      "id": "l76lfrh",
      "body": "[removed]",
      "created_utc": 1717569225.0,
      "score": -22
    },
    {
      "id": "l76qcx5",
      "body": "So you postponed it?",
      "created_utc": 1717572629.0,
      "score": -7
    },
    {
      "id": "l76r347",
      "body": "My sister gave up on me",
      "created_utc": 1717573170.0,
      "score": 46
    },
    {
      "id": "l77dr03",
      "body": "My sibling is the opposite",
      "created_utc": 1717588058.0,
      "score": 6
    },
    {
      "id": "l78ar62",
      "body": "I always wish I had a sibling",
      "created_utc": 1717601043.0,
      "score": 3
    },
    {
      "id": "l7ciqo1",
      "body": "How do you hold onto that 1% of hope in life, when you’re ready to accept it all?",
      "created_utc": 1717665472.0,
      "score": 2
    },
    {
      "id": "l79mso9",
      "body": "Poor wording on this sub.  Like saying sub in r/dom.. js.. \n\nOp: hope you live the shit out of life, you live so much you'll live enought for at least 2 ppl.",
      "created_utc": 1717617114.0,
      "score": 0
    },
    {
      "id": "l7h3ao7",
      "body": "He's alive ",
      "created_utc": 1717729301.0,
      "score": 1
    },
    {
      "id": "l7exg7f",
      "body": "What if after everything that has happened to you, you’ve lost all joyful moments and can’t genuinely be happy anymore? Id love to find a solid reason for myself to stick around but I’ve ran out…",
      "created_utc": 1717700142.0,
      "score": 1
    },
    {
      "id": "l783hsj",
      "body": "Sometimes it really doesn't, unfortunately",
      "created_utc": 1717598533.0,
      "score": 6
    },
    {
      "id": "l783nnx",
      "body": "Is OP still alive?",
      "created_utc": 1717598590.0,
      "score": 1
    },
    {
      "id": "l79ma9t",
      "body": "Hugs for all",
      "created_utc": 1717616944.0,
      "score": 1
    },
    {
      "id": "l7aipkh",
      "body": "yeah im doing fine!",
      "created_utc": 1717628328.0,
      "score": 19
    },
    {
      "id": "l7awhw8",
      "body": "It sounds like it wasn't your time btw",
      "created_utc": 1717633820.0,
      "score": 1
    },
    {
      "id": "l81rrxi",
      "body": "🤣🤣🤣",
      "created_utc": 1718067310.0,
      "score": 1
    },
    {
      "id": "l76vm9i",
      "body": "That must hurt. My sister is becoming more and more distant and people around me don't like me. As soon as I open up to people, I become really annoying.",
      "created_utc": 1717576529.0,
      "score": 38
    },
    {
      "id": "l7a4un5",
      "body": "i will be your new sister",
      "created_utc": 1717623194.0,
      "score": 8
    },
    {
      "id": "l78womj",
      "body": "Hey man, I'm sorry, why did she?",
      "created_utc": 1717608391.0,
      "score": 3
    },
    {
      "id": "l79d2x7",
      "body": "Same",
      "created_utc": 1717613873.0,
      "score": 2
    },
    {
      "id": "l79n3fg",
      "body": "Oh shit; that did not occur to me 😭😭😭\n\nI wasn’t thinking about it like that",
      "created_utc": 1717617214.0,
      "score": 3
    },
    {
      "id": "l7hmxiw",
      "body": "I’ve ran out too. And then I found out that for me, the fact that I couldn’t feel joy anymore was a medical codition that I had to fix with the help of my therapist and my doctor. I’m ofcource not saying, taht thats the case for everyone, but you don’t have to search for reasons to stick around alone. People are subjective. Meybe there is a reason you just aren’t able to see.",
      "created_utc": 1717739731.0,
      "score": 1
    },
    {
      "id": "l7aqj51",
      "body": "Hi friend! I'm very happy to see you're still around",
      "created_utc": 1717631399.0,
      "score": 3
    },
    {
      "id": "l7avg4g",
      "body": "hello! so glad to see you still here! hopefully tomorrow is a little brighter as well :3",
      "created_utc": 1717633389.0,
      "score": 3
    },
    {
      "id": "l82f31x",
      "body": "I'm so SO glad that you are.  I'm rarely on Reddit, but if you would like to talk, anytime, I am here 🤗.",
      "created_utc": 1718077354.0,
      "score": 1
    },
    {
      "id": "l82mh5j",
      "body": "Awesome 🤗!",
      "created_utc": 1718081188.0,
      "score": 1
    },
    {
      "id": "l82qi1z",
      "body": "Yah!  Awesome!  Every want to talk, I am here 🤗.",
      "created_utc": 1718083513.0,
      "score": 1
    },
    {
      "id": "l82ulgm",
      "body": "🤗",
      "created_utc": 1718086050.0,
      "score": 1
    },
    {
      "id": "l77gkq6",
      "body": "Most ppl don’t have the emotional maturity, and overall maturity to be able to support ppl, or even be understanding of ppl.\n\nYou just gotta be understanding towards yourself. There’s nothing wrong with you, so learn to be understanding to yourself.\n\nThis goes for OP also",
      "created_utc": 1717589427.0,
      "score": 25
    },
    {
      "id": "l7ahqbj",
      "body": "i relate so badly, they act like they care abt me and shit in the beginning and rn they would just trash me if any opportunity exists for their betterment",
      "created_utc": 1717627951.0,
      "score": 6
    },
    {
      "id": "l77yb5s",
      "body": "Me 2",
      "created_utc": 1717596701.0,
      "score": 4
    },
    {
      "id": "l78wsfw",
      "body": "Many don't care about others I think, I feel the same towards people I typically meet, why do you think this is the case?",
      "created_utc": 1717608426.0,
      "score": 6
    },
    {
      "id": "l7c2ol6",
      "body": "You just made me tear up🥹❤️ thank you so much. Losing family has been the most heart breaking and gut wrenching experience.",
      "created_utc": 1717654060.0,
      "score": 2
    },
    {
      "id": "l7c2xdd",
      "body": "Thank you so much. The reason is actually so infuriating and stupid that I can’t even begin to explain it. It makes me shake and cry.",
      "created_utc": 1717654218.0,
      "score": 2
    },
    {
      "id": "l82mk68",
      "body": "Me too 😀!",
      "created_utc": 1718081235.0,
      "score": 1
    },
    {
      "id": "l7bukuz",
      "body": "Your sister acted like she cares about you?",
      "created_utc": 1717649230.0,
      "score": 2
    },
    {
      "id": "l7cfrkt",
      "body": "just about everyone, even my parents just take care of me because its a responsibility (i am 20 yo)",
      "created_utc": 1717663277.0,
      "score": 3
    },
    {
      "id": "l7o0fxt",
      "body": "My parents pretend to care about me, but either they don't or I'm schizophrenic.",
      "created_utc": 1717849269.0,
      "score": 1
    }
  ]
}