{
    "id": "1kfg4h9",
    "title": "I regret not killing myself when I was younger.",
    "selftext": "surprised make",
    "created_utc": "2025-05-05T16:34:59",
    "score": 786,
    "num_comments": 217,
    "url": "https://www.reddit.com/r/depression/comments/1kfg4h9/i_regret_not_killing_myself_when_i_was_younger/",
    "comments": [
        {
            "id": "mqqqhxg",
            "body": "regret kill every day past two year",
            "created_utc": "2025-05-05T17:38:54",
            "score": 157
        },
        {
            "id": "mqqvzby",
            "body": "sit think friend sorry us hope get well soon still mom deal shit soon go though spray thesis fuck thought place",
            "created_utc": "2025-05-05T18:04:56",
            "score": 78
        },
        {
            "id": "mqquoyx",
            "body": "mood idea make almost stop plan anything past",
            "created_utc": "2025-05-05T17:58:43",
            "score": 115
        },
        {
            "id": "mqqmlpl",
            "body": "wish kill",
            "created_utc": "2025-05-05T17:20:31",
            "score": 42
        },
        {
            "id": "mqqs6l2",
            "body": "wish do twenty disappoint everyone",
            "created_utc": "2025-05-05T17:46:53",
            "score": 34
        },
        {
            "id": "mqqqujw",
            "body": "know honest",
            "created_utc": "2025-05-05T17:40:33",
            "score": 25
        },
        {
            "id": "mqro9ad",
            "body": "marry two kid wife supportive decade believe get well fail attempt teenager bring much suffering world try hard pill cut deep imagine another year like",
            "created_utc": "2025-05-05T20:23:38",
            "score": 23
        },
        {
            "id": "mqr90oo",
            "body": "agree perfectly good plan oh well",
            "created_utc": "2025-05-05T19:08:55",
            "score": 16
        },
        {
            "id": "mqqktne",
            "body": "th birthday come never ever one thought would alive long",
            "created_utc": "2025-05-05T17:12:06",
            "score": 24
        },
        {
            "id": "mqqz7u6",
            "body": "make get well worse well bad",
            "created_utc": "2025-05-05T18:20:41",
            "score": 23
        },
        {
            "id": "mqrmudg",
            "body": "honestly life get bad every day someone like really point live still year away already feel like live",
            "created_utc": "2025-05-05T20:16:54",
            "score": 11
        },
        {
            "id": "mqtpbyb",
            "body": "mate wish would never come earth think",
            "created_utc": "2025-05-06T03:11:39",
            "score": 8
        },
        {
            "id": "mquomo5",
            "body": "believe god truly exist die sleep truly exist lot shit would happen every night flick god hope piss enough wake hate far make dead end life fill misery disappointment fuck big joke ask",
            "created_utc": "2025-05-06T08:23:29",
            "score": 11
        },
        {
            "id": "mqv1jpz",
            "body": "delete",
            "created_utc": "2025-05-06T10:36:28",
            "score": 6
        },
        {
            "id": "mqu7u7e",
            "body": "one thing horrified remember get first thought commit first attempt around turn fucking scared continue like parasite know need kill drive living isolation ignorance long genuinely keep think nihilism fear kick would death matter would god look upon pass painful choice anymore",
            "created_utc": "2025-05-06T05:32:39",
            "score": 5
        },
        {
            "id": "mqughze",
            "body": "turn lose ever give much thought person know never go make big life although scenario head would state otherwise almost quarter life go nothing show peer stable successful life know lose golden year life one build well never know tf wanted life live moment worry future would earn live parent always supportive whatever wish work someone never want anything know disappoint parent every breath take would well go world always one voice head want least repay thing do regardless worthlessness moment voice start fade begin accept fate doom forever",
            "created_utc": "2025-05-06T06:56:04",
            "score": 5
        },
        {
            "id": "mqqp2h8",
            "body": "feel similar possible look life different filter possible something good happen year old almost complete failure almost everything good relationship year hope get back time future",
            "created_utc": "2025-05-05T17:32:05",
            "score": 9
        },
        {
            "id": "mqrimkv",
            "body": "relate",
            "created_utc": "2025-05-05T19:56:29",
            "score": 3
        },
        {
            "id": "mqug4y7",
            "body": "somehow make honest would rather",
            "created_utc": "2025-05-06T06:52:26",
            "score": 5
        },
        {
            "id": "mqxjufl",
            "body": "real go university attempt wish fail",
            "created_utc": "2025-05-06T18:45:52",
            "score": 3
        },
        {
            "id": "mqrgrsh",
            "body": "fear death powerful thing thing keep alive parodically fear death also source anxiety ocd despair",
            "created_utc": "2025-05-05T19:47:30",
            "score": 7
        },
        {
            "id": "mqruiw3",
            "body": "attempe last year wish call help",
            "created_utc": "2025-05-05T20:54:05",
            "score": 3
        },
        {
            "id": "mqs73xe",
            "body": "turn week depress since feel every word",
            "created_utc": "2025-05-05T21:58:58",
            "score": 3
        },
        {
            "id": "mqsr48c",
            "body": "feel regret survive motorcycle crash",
            "created_utc": "2025-05-05T23:50:38",
            "score": 3
        },
        {
            "id": "mqsu7ss",
            "body": "",
            "created_utc": "2025-05-06T00:08:07",
            "score": 3
        },
        {
            "id": "mqsuha5",
            "body": "work hard everyday hope life get well barely ever see hard optimistic life",
            "created_utc": "2025-05-06T00:09:38",
            "score": 3
        },
        {
            "id": "mqsxsx5",
            "body": "hey thing use feel like killing since pussy choose live anymore aka like zombie",
            "created_utc": "2025-05-06T00:28:43",
            "score": 3
        },
        {
            "id": "mqtb9a6",
            "body": "know feel lose count many time try kill",
            "created_utc": "2025-05-06T01:46:06",
            "score": 3
        },
        {
            "id": "mqtr7s8",
            "body": "regret cross late thirty year could go back would help people get responsibility take care indefinitely",
            "created_utc": "2025-05-06T03:24:34",
            "score": 3
        },
        {
            "id": "mqtsk6j",
            "body": "know feels work barely afford living feeling like pointless day make go wait oh right choose tooreally get plan life right kind thing needless say hope get well honestly think would find odd tell reason do think different way die sound painful risk survive even fuck condition do anything",
            "created_utc": "2025-05-06T03:34:03",
            "score": 3
        },
        {
            "id": "mqtxkkq",
            "body": "samei always regret live",
            "created_utc": "2025-05-06T04:10:21",
            "score": 3
        },
        {
            "id": "mqty8jm",
            "body": "also feel way lot recently",
            "created_utc": "2025-05-06T04:15:29",
            "score": 3
        },
        {
            "id": "mqubpvn",
            "body": "want die",
            "created_utc": "2025-05-06T06:08:35",
            "score": 3
        },
        {
            "id": "mquon7u",
            "body": "point care live nobody care literally none wish die accident want anyone suffer hope god fulfill wish one day",
            "created_utc": "2025-05-06T08:23:40",
            "score": 3
        },
        {
            "id": "mqv8c4k",
            "body": "man mee do",
            "created_utc": "2025-05-06T11:31:21",
            "score": 3
        },
        {
            "id": "mqzbzb5",
            "body": "delete",
            "created_utc": "2025-05-07T00:11:14",
            "score": 3
        },
        {
            "id": "mqqss9d",
            "body": "relatable somehow still hope well future",
            "created_utc": "2025-05-05T17:49:43",
            "score": 2
        },
        {
            "id": "mqr12up",
            "body": "kind really regret kill regret general",
            "created_utc": "2025-05-05T18:29:48",
            "score": 2
        },
        {
            "id": "mqrelxm",
            "body": "omg family would gotten try young luck",
            "created_utc": "2025-05-05T19:36:51",
            "score": 2
        },
        {
            "id": "mqtja5l",
            "body": "",
            "created_utc": "2025-05-06T02:32:59",
            "score": 2
        },
        {
            "id": "mqtsacm",
            "body": "surprised make honest make attempt go way",
            "created_utc": "2025-05-06T03:32:07",
            "score": 2
        },
        {
            "id": "mqtt314",
            "body": "tired",
            "created_utc": "2025-05-06T03:37:43",
            "score": 2
        },
        {
            "id": "mqtvicp",
            "body": "lmao never mean",
            "created_utc": "2025-05-06T03:55:10",
            "score": 2
        },
        {
            "id": "mqvoprz",
            "body": "wish kill last year time fly get anywhere tired waste time nothing",
            "created_utc": "2025-05-06T13:18:20",
            "score": 2
        },
        {
            "id": "mqw9lv5",
            "body": "also regret reason still breathe kid dependency still fight urge dailyweeklyrandom go even around life",
            "created_utc": "2025-05-06T15:05:49",
            "score": 2
        },
        {
            "id": "mqxt5x5",
            "body": "world stop spin year old die hour bear like nurse tell mom might birth",
            "created_utc": "2025-05-06T19:30:56",
            "score": 2
        },
        {
            "id": "mqxyle3",
            "body": "feel every day year try obviously fail shortly meet husband tell would try well relationship fail two kid dog wake every day wish wishing would try wish would even keep reach talk people never want live long exhausting hurt recently also diagnose bipolar explain many thing say alone purple heart",
            "created_utc": "2025-05-06T19:56:47",
            "score": 2
        },
        {
            "id": "mqycfgx",
            "body": "know situation would turn next year would end",
            "created_utc": "2025-05-06T21:01:45",
            "score": 2
        },
        {
            "id": "mqyyugw",
            "body": "wish would do help pay rent",
            "created_utc": "2025-05-06T22:57:36",
            "score": 2
        },
        {
            "id": "mqz8opk",
            "body": "relate heavy make attempt summer since life get much bad fantasize much well would actually",
            "created_utc": "2025-05-06T23:52:10",
            "score": 2
        },
        {
            "id": "mr0blzu",
            "body": "want like late twelve early thirteen covid month regret follow understand op",
            "created_utc": "2025-05-07T03:46:08",
            "score": 2
        },
        {
            "id": "mr0q0rg",
            "body": "turn month highs good dip even want live another day",
            "created_utc": "2025-05-07T05:39:46",
            "score": 2
        },
        {
            "id": "mr2g5h1",
            "body": "make really think would die life surprisingly hard average joe",
            "created_utc": "2025-05-07T14:06:14",
            "score": 2
        },
        {
            "id": "mr35vwe",
            "body": "also suddenly tell good friend want fly blue sky never come back disappear sound like silly joke back yet wonder actually want die scared say loud",
            "created_utc": "2025-05-07T16:12:07",
            "score": 2
        },
        {
            "id": "mqqgojv",
            "body": "understand feel way hey struggle hardwork put see today throw away tomorrow well today hope good life ahead",
            "created_utc": "2025-05-05T16:52:13",
            "score": 4
        },
        {
            "id": "mqr8xlx",
            "body": "wish kill",
            "created_utc": "2025-05-05T19:08:30",
            "score": 2
        },
        {
            "id": "mqsf3dz",
            "body": "struggle time want go pain put people pain suicide much tiring know lose scared anything",
            "created_utc": "2025-05-05T22:43:28",
            "score": 3
        },
        {
            "id": "mqqokpw",
            "body": "end everything close really weird feeling",
            "created_utc": "2025-05-05T17:29:46",
            "score": 2
        },
        {
            "id": "mqu38ns",
            "body": "anyone want talk everyone red heart life always sunshine rainbow need look bright side thing go nature see beautiful life really",
            "created_utc": "2025-05-06T04:53:19",
            "score": 3
        },
        {
            "id": "mqrzidz",
            "body": "find peace",
            "created_utc": "2025-05-05T21:19:06",
            "score": 1
        },
        {
            "id": "mr55kng",
            "body": "reason take final step require energy passion emotion something fade age people underestimate much care life end itwhen one indifferent everything hard find motivation anything let alone something big ending need little bit madness take final step point year first think terminate say worthwhile life shit forecast would",
            "created_utc": "2025-05-07T21:57:20",
            "score": 1
        },
        {
            "id": "mr5xv2g",
            "body": "agree wish would gotten way",
            "created_utc": "2025-05-08T00:38:29",
            "score": 1
        },
        {
            "id": "mr60tl2",
            "body": "get well everything ever give happiness pull away could experience grief",
            "created_utc": "2025-05-08T00:55:44",
            "score": 1
        },
        {
            "id": "mr6njyn",
            "body": "stay strong know go stay strong find someone support",
            "created_utc": "2025-05-08T03:11:13",
            "score": 1
        },
        {
            "id": "mr7c2oe",
            "body": "also everything go worse bad life feel able pull freaking trigger need help brave enough speak able good step",
            "created_utc": "2025-05-08T06:32:08",
            "score": 1
        },
        {
            "id": "mr8hsh2",
            "body": "surprised make honest",
            "created_utc": "2025-05-08T12:43:05",
            "score": 1
        },
        {
            "id": "mr8wsnk",
            "body": "relatable year ago would dead instead still live shitty life",
            "created_utc": "2025-05-08T14:07:07",
            "score": 1
        },
        {
            "id": "mr9s2wn",
            "body": "think thing moment glad alive sure overall think everyday way live family would think",
            "created_utc": "2025-05-08T16:40:42",
            "score": 1
        },
        {
            "id": "mra05k2",
            "body": "long live high chance ul one day grateful gna die one day anyways might well see life might offer imagine one day die natural cause feel like go blink eye anyways hopefully well future someday clink beer mug",
            "created_utc": "2025-05-08T17:19:33",
            "score": 1
        },
        {
            "id": "mra10y7",
            "body": "feel like would yet scare disappoint family tired",
            "created_utc": "2025-05-08T17:23:43",
            "score": 1
        },
        {
            "id": "mra2pit",
            "body": "glad survive killing die cardiac arrest body bag life support move ventilator regret family scoop vomit mouth chest compression aspiratie regret tear regret put mom die dad stroke two year later head stop think cause happen therapist say happen never think would make past grow faith keep easy well send love blessing get easy still struggle mental health get easy quit drink use also life saver even though make thing easy time",
            "created_utc": "2025-05-08T17:31:51",
            "score": 1
        },
        {
            "id": "mrbc5cv",
            "body": "glad make till",
            "created_utc": "2025-05-08T21:14:34",
            "score": 1
        },
        {
            "id": "mrbnx8n",
            "body": "want die turning feel ashamed much coward",
            "created_utc": "2025-05-08T22:18:51",
            "score": 1
        },
        {
            "id": "mrcyetv",
            "body": "write first suicide note rd grade thought could get well get big almost give alive knew dad would miss even though know mother would forget everyday like constantly fantasize death wish go everyday everyone would well without sometimes little thing make happy make feel good glad experience undo decision even alone eat cake least cake time exhaustion depression gets say know damn well sleep unless knife pill rope near case live anymore immediate way lol",
            "created_utc": "2025-05-09T03:05:14",
            "score": 1
        },
        {
            "id": "mrdm9jd",
            "body": "make two week feel like fluke honest prepare ahead expect make long think thing would still terrible",
            "created_utc": "2025-05-09T06:20:21",
            "score": 1
        },
        {
            "id": "mremf25",
            "body": "attempt th grade bad mistake successful always scare try",
            "created_utc": "2025-05-09T12:03:13",
            "score": 1
        },
        {
            "id": "mrgejrz",
            "body": "honest regret aborted mom life hell since birth ptsd negligence birth parent malnourishment lot abuse since young child also autism get social anxiety major depression age make social life live hell never even romantic relationship life even though top debilating anhedonia dpdr fatigue last year know still fight think autopilot way know thing change much change value anyone society loner life truly rollercoaster dissapointment end",
            "created_utc": "2025-05-09T17:48:53",
            "score": 1
        },
        {
            "id": "mrhpzhe",
            "body": "make",
            "created_utc": "2025-05-09T21:55:25",
            "score": 1
        },
        {
            "id": "mrj86ou",
            "body": "wish do disappoint everyone",
            "created_utc": "2025-05-10T03:39:04",
            "score": 1
        },
        {
            "id": "mrkgp0f",
            "body": "couple month wish would done teen daughter",
            "created_utc": "2025-05-10T10:36:34",
            "score": 1
        },
        {
            "id": "mrl8ofg",
            "body": "think back everything would miss year pain",
            "created_utc": "2025-05-10T13:59:48",
            "score": 1
        },
        {
            "id": "mrlbroa",
            "body": "thing stop daughter kid leave would hurt would long time ago day grandkid mean push edge recently try take well care buy new clothe start go community center make friend little joy go everytime go together get ask mother old happen times community center card game divide age group yet someone ask mother stay home ever want go avoid hurt matter try happiness life",
            "created_utc": "2025-05-10T14:17:56",
            "score": 1
        },
        {
            "id": "mrmmwv7",
            "body": "feel everyday sorry we",
            "created_utc": "2025-05-10T18:35:58",
            "score": 1
        },
        {
            "id": "mrn0767",
            "body": "yeah unfortunately kind come say something encourage today sorry suffer life exhaust know many day leave feel low people reach well even find word today",
            "created_utc": "2025-05-10T19:52:38",
            "score": 1
        },
        {
            "id": "mrnvb6g",
            "body": "regret waking attempt still lazy even",
            "created_utc": "2025-05-10T22:58:25",
            "score": 1
        },
        {
            "id": "mroorhn",
            "body": "ready even feel utter peace wash people talk plan get rid life alas really stupid go hey therapy session tomorrow maybe give living one last chance work tomorrow stupid stupid stupid hard time lie guilt therapist know get day parent still seem take seriously get would want exist agree downer lmao",
            "created_utc": "2025-05-11T02:09:00",
            "score": 1
        },
        {
            "id": "mrp0eal",
            "body": "upset religion die puberty immediately go heaven get suicidal two year two year depress two year early would probably dead",
            "created_utc": "2025-05-11T03:30:07",
            "score": 1
        },
        {
            "id": "mrp2qq3",
            "body": "fuck get life peak wish strength life hell see end sight",
            "created_utc": "2025-05-11T03:47:06",
            "score": 1
        },
        {
            "id": "mrr4di9",
            "body": "bro even know ever go make past need hug cigarette know",
            "created_utc": "2025-05-11T14:24:17",
            "score": 1
        },
        {
            "id": "mrred7w",
            "body": "go kill turn",
            "created_utc": "2025-05-11T15:18:10",
            "score": 1
        },
        {
            "id": "mrrjyg8",
            "body": "loser burden parent feel guilty exist",
            "created_utc": "2025-05-11T15:47:58",
            "score": 1
        },
        {
            "id": "mrv1f11",
            "body": "wish dead birth god ever bullshit make",
            "created_utc": "2025-05-12T04:18:28",
            "score": 1
        },
        {
            "id": "mrva1zv",
            "body": "want easy way guilt feel leave family behind unbearable even though nobody ever mom go one friend would never want make anyone suffer idea even go age feel unmotivated hopeless",
            "created_utc": "2025-05-12T05:34:07",
            "score": 1
        },
        {
            "id": "mrvt6cp",
            "body": "tell reason",
            "created_utc": "2025-05-12T08:50:50",
            "score": 1
        },
        {
            "id": "mrwchmq",
            "body": "wait seriously hope find someone love something push",
            "created_utc": "2025-05-12T11:48:47",
            "score": 1
        },
        {
            "id": "mrwi22e",
            "body": "attempt however mother rush stop middle thought exact thought turn idea jump time time terrify think still",
            "created_utc": "2025-05-12T12:27:56",
            "score": 1
        },
        {
            "id": "mrwtka2",
            "body": "say want die since ten next month nothing change",
            "created_utc": "2025-05-12T13:38:49",
            "score": 1
        },
        {
            "id": "ms6f2ll",
            "body": "want since pray make",
            "created_utc": "2025-05-13T23:11:29",
            "score": 1
        },
        {
            "id": "mtztihs",
            "body": "ever since ball regret even ball donf know would",
            "created_utc": "2025-05-24T11:53:49",
            "score": 1
        },
        {
            "id": "mumjlug",
            "body": "try fail everyday recently wish work",
            "created_utc": "2025-05-28T01:51:17",
            "score": 1
        },
        {
            "id": "mqr8r1k",
            "body": "get something inside keep go even everything feel hopeless part refuse give nothing dark time break try well still inner strength real everyone",
            "created_utc": "2025-05-05T19:07:36",
            "score": 0
        },
        {
            "id": "mqsiue0",
            "body": "remove",
            "created_utc": "2025-05-05T23:04:33",
            "score": -5
        },
        {
            "id": "mqqmdv7",
            "body": "help",
            "created_utc": "2025-05-05T17:19:28",
            "score": -3
        },
        {
            "id": "mquenrd",
            "body": "",
            "created_utc": "2025-05-06T06:37:26",
            "score": 17
        },
        {
            "id": "mrreg2o",
            "body": "",
            "created_utc": "2025-05-11T15:18:35",
            "score": 2
        },
        {
            "id": "mrukamx",
            "body": "understand",
            "created_utc": "2025-05-12T02:12:14",
            "score": 2
        },
        {
            "id": "mqswvdm",
            "body": "feel parent love know ever give sheer disappointment one another sake make feel bad pussy already probably do",
            "created_utc": "2025-05-06T00:23:18",
            "score": 24
        },
        {
            "id": "mqz8i60",
            "body": "family hate one miss good enough anything even end suffering know",
            "created_utc": "2025-05-06T23:51:09",
            "score": 7
        },
        {
            "id": "mr56bu0",
            "body": "plan even though close parent feel right mum particular great life pass though social obligation tap",
            "created_utc": "2025-05-07T22:01:21",
            "score": 4
        },
        {
            "id": "mqt1n5a",
            "body": "seem plan although feel persevere long enough",
            "created_utc": "2025-05-06T00:50:35",
            "score": 5
        },
        {
            "id": "mrn0d53",
            "body": "damn boat still around mom struggle like crazy find something else keep pass one day know",
            "created_utc": "2025-05-10T19:53:36",
            "score": 2
        },
        {
            "id": "mrr4vvv",
            "body": "",
            "created_utc": "2025-05-11T14:27:08",
            "score": 2
        },
        {
            "id": "mqts127",
            "body": "every year go bad thing happen wish avoid long ago add anything good anyone even nothing good offer world",
            "created_utc": "2025-05-06T03:30:18",
            "score": 10
        },
        {
            "id": "mqsum05",
            "body": "feel",
            "created_utc": "2025-05-06T00:10:23",
            "score": 5
        },
        {
            "id": "mr575cf",
            "body": "disappointment other shame pointless life live dead inside emotion passion energy motivation anything need lot drive lot madness end predominantly impulsive rash people end neither constant low mood lack interest life nothing ever good sense total trapness consider coward end course comment one else",
            "created_utc": "2025-05-07T22:05:46",
            "score": 6
        },
        {
            "id": "mqsuq9c",
            "body": "turn year afraid club",
            "created_utc": "2025-05-06T00:11:03",
            "score": 10
        },
        {
            "id": "mqzzkx3",
            "body": "marry one kid love family also wish use worry hurt parent want hurt wife kid trap",
            "created_utc": "2025-05-07T02:28:29",
            "score": 2
        },
        {
            "id": "mrde4vw",
            "body": "fuck get way",
            "created_utc": "2025-05-09T05:06:37",
            "score": 2
        },
        {
            "id": "mqyx3t7",
            "body": "feel year marry son stay fear burden family dreadful existence feel stuck way torture",
            "created_utc": "2025-05-06T22:48:09",
            "score": 2
        },
        {
            "id": "mqqlx9w",
            "body": "hey share feeling",
            "created_utc": "2025-05-05T17:17:18",
            "score": 4
        },
        {
            "id": "mqtt31c",
            "body": "lately get bad meh bad meh well quite",
            "created_utc": "2025-05-06T03:37:43",
            "score": 12
        },
        {
            "id": "mqsuxic",
            "body": "could see",
            "created_utc": "2025-05-06T00:12:12",
            "score": 2
        },
        {
            "id": "mr5g3bl",
            "body": "make bad fighting since life suck",
            "created_utc": "2025-05-07T22:56:02",
            "score": 2
        },
        {
            "id": "mrdebov",
            "body": "yessss",
            "created_utc": "2025-05-09T05:08:15",
            "score": 1
        },
        {
            "id": "mrdefp2",
            "body": "get thing",
            "created_utc": "2025-05-09T05:09:12",
            "score": 2
        },
        {
            "id": "mrdejnw",
            "body": "sorry suffering",
            "created_utc": "2025-05-09T05:10:08",
            "score": 3
        },
        {
            "id": "mrdeyts",
            "body": "think suffer least understand live long whole live scam world offer many thing available everyone money enjoy even money die everyone try help one another consume spend time still breath come wedding never find person seem find person baby eveyrthe money spend money day die fucking die",
            "created_utc": "2025-05-09T05:13:42",
            "score": 1
        },
        {
            "id": "mquvoqk",
            "body": "fear death mean fear",
            "created_utc": "2025-05-06T09:40:11",
            "score": 1
        },
        {
            "id": "mqtz2db",
            "body": "regret surviving make happy person could live life",
            "created_utc": "2025-05-06T04:21:44",
            "score": 1
        },
        {
            "id": "mrnq4tn",
            "body": "",
            "created_utc": "2025-05-10T22:25:14",
            "score": 1
        },
        {
            "id": "mr6nfe7",
            "body": "alright",
            "created_utc": "2025-05-08T03:10:20",
            "score": 2
        },
        {
            "id": "mr58ll2",
            "body": "life one big let would done year ago would miss anything",
            "created_utc": "2025-05-07T22:13:44",
            "score": 1
        },
        {
            "id": "mqrbxtb",
            "body": "ah yes sink cost fallacy",
            "created_utc": "2025-05-05T19:23:27",
            "score": 2
        },
        {
            "id": "mqtu8f1",
            "body": "",
            "created_utc": "2025-05-06T03:45:57",
            "score": 1
        },
        {
            "id": "mresel0",
            "body": "different",
            "created_utc": "2025-05-09T12:42:47",
            "score": 1
        },
        {
            "id": "mri18o7",
            "body": "man",
            "created_utc": "2025-05-09T23:01:45",
            "score": 1
        },
        {
            "id": "mqtvyib",
            "body": "rimfixednow",
            "created_utc": "2025-05-06T03:58:28",
            "score": 6
        },
        {
            "id": "mqrb27y",
            "body": "",
            "created_utc": "2025-05-05T19:19:05",
            "score": 3
        },
        {
            "id": "mqrepp2",
            "body": "help world actually good place everyone tell we focus positive merely try convince truth",
            "created_utc": "2025-05-05T19:37:22",
            "score": 3
        },
        {
            "id": "mr5huj6",
            "body": "",
            "created_utc": "2025-05-07T23:06:09",
            "score": 3
        },
        {
            "id": "mqt1f37",
            "body": "homie everything attempt failure wait happen shit ass deadend job life never high sink low every day sorry homie",
            "created_utc": "2025-05-06T00:49:19",
            "score": 17
        },
        {
            "id": "mrrk9gf",
            "body": "real af sorry go shit literally life disappointment parent people always tell disappointment failure",
            "created_utc": "2025-05-11T15:49:38",
            "score": 1
        },
        {
            "id": "mqzatd1",
            "body": "like carlin say give fuck turn country anywhere else matter think human game long ago high priest trader take say find fun laugh absurdity world go motorcycle help plus someone else fuck bike",
            "created_utc": "2025-05-07T00:04:27",
            "score": 6
        },
        {
            "id": "mqt240x",
            "body": "easy focus moment fuck later go suck anyways time energy well spend mitigate present pain weed help",
            "created_utc": "2025-05-06T00:53:17",
            "score": 8
        },
        {
            "id": "mrdmfmo",
            "body": "anybody else still hold pet feel like would miss much bother",
            "created_utc": "2025-05-09T06:21:56",
            "score": 1
        },
        {
            "id": "mqzx8cq",
            "body": "burden sorry feel way stay family please believe worth live worth live son partner people life worth live reason",
            "created_utc": "2025-05-07T02:14:40",
            "score": 5
        },
        {
            "id": "mqwquwb",
            "body": "fear die process really really fear exist",
            "created_utc": "2025-05-06T16:28:57",
            "score": 3
        },
        {
            "id": "mrybsi2",
            "body": "look like come wrong subreddit",
            "created_utc": "2025-05-12T18:09:25",
            "score": 2
        },
        {
            "id": "mquj1cb",
            "body": "stick last year feel grow anything person sad angry time everyday wish go bed wake tomorrow shit reality average person zero motivation happen try something always fail go anywhere ashamed keep conversation always worry make fool always even walk street feel stress really wish never bear somebody else could take place enjoy life something joyful regret still alive sorry feel sorry feel like",
            "created_utc": "2025-05-06T07:22:50",
            "score": 22
        },
        {
            "id": "mqzdneq",
            "body": "know point learn ride bike even drive car motorcycle terrible idea high chance stay alive disability",
            "created_utc": "2025-05-07T00:21:00",
            "score": 4
        },
        {
            "id": "mrojx5z",
            "body": "might brink insanity since admit psychosis instead seek escape lean pain see turn something say pain power depend use want put test",
            "created_utc": "2025-05-11T01:37:35",
            "score": 3
        },
        {
            "id": "mrhwbxp",
            "body": "yeah dog stress feel sucide selfish end think sometimes think time come eventually like sort accident would well offing least people get hurt fact dead",
            "created_utc": "2025-05-09T22:32:23",
            "score": 2
        },
        {
            "id": "mrjgyxf",
            "body": "people barely care parent doubt majority give shit pet",
            "created_utc": "2025-05-10T04:47:31",
            "score": 0
        },
        {
            "id": "mrznrbi",
            "body": "well depress hell",
            "created_utc": "2025-05-12T22:12:25",
            "score": 2
        },
        {
            "id": "mr9slag",
            "body": "think time give place someone want someone terminal illness die injury would gladly trade could live everyone say alive gift feel like punishment",
            "created_utc": "2025-05-08T16:43:10",
            "score": 8
        },
        {
            "id": "mrlcr7m",
            "body": "like look inside write",
            "created_utc": "2025-05-10T14:23:33",
            "score": 3
        },
        {
            "id": "mrbn9p4",
            "body": "put shoe never try push hard time life live sit think thing enjoy try milk enjoyment know word inspire writer hope help",
            "created_utc": "2025-05-08T22:15:06",
            "score": 2
        },
        {
            "id": "mqzev6v",
            "body": "check george carlin quote brain dropping good book hope find well day soon friend",
            "created_utc": "2025-05-07T00:28:16",
            "score": 3
        },
        {
            "id": "mrzxtek",
            "body": "certainly plan learn teach believe work would actually love",
            "created_utc": "2025-05-12T23:09:48",
            "score": 1
        },
        {
            "id": "mrhx273",
            "body": "yeah get talk hotline counselor last night like fine reason hold long cat dog would miss much cuddling day today animal intuitive hope well day ahead we",
            "created_utc": "2025-05-09T22:36:44",
            "score": 1
        },
        {
            "id": "mrjhk7u",
            "body": "much care parent personally parent ever see extension dad always want go law school never finish mom want writer never pursue write full time parent would probably miss mom life alone would lonely feel genuine need affection pet hence guilt",
            "created_utc": "2025-05-10T04:52:06",
            "score": 1
        },
        {
            "id": "mrobd6u",
            "body": "",
            "created_utc": "2025-05-11T00:41:17",
            "score": 2
        },
        {
            "id": "mqzlj9h",
            "body": "thank",
            "created_utc": "2025-05-07T01:07:41",
            "score": 3
        }
    ]
}